parse_type/__init__.py
parse_type/builder.py
parse_type/cardinality.py
parse_type/cardinality_field.py
parse_type/cfparse.py
parse_type/parse.py
parse_type/parse_util.py
radish_parse_type-0.3.5.dist-info/DESCRIPTION.rst
radish_parse_type-0.3.5.dist-info/METADATA
radish_parse_type-0.3.5.dist-info/RECORD
radish_parse_type-0.3.5.dist-info/WHEEL
radish_parse_type-0.3.5.dist-info/metadata.json
radish_parse_type-0.3.5.dist-info/top_level.txt
radish_parse_type-0.3.5.dist-info/zip-safe
tasks/__init__.py
tasks/__main__.py
tasks/_setup.py
tasks/clean.py
tasks/docs.py
tasks/py.requirements.txt
tasks/test.py
tasks/_vendor/README.rst
tasks/_vendor/invoke.zip
tasks/_vendor/path.py
tasks/_vendor/pathlib.py
tasks/_vendor/six.py
