Metadata-Version: 2.0
Name: radish-parse-type
Version: 0.3.5
Summary: Simplifies to build parse types based on the parse module
Home-page: https://github.com/jenisys/parse_type
Author: Timo Furrer
Author-email: tuxtimo@gmail.com
License: BSD
Download-URL: http://pypi.python.org/pypi/parse_type
Keywords: parse,parsing
Platform: any
Classifier: Development Status :: 4 - Beta
Classifier: Environment :: Console
Classifier: Environment :: Web Environment
Classifier: Intended Audience :: Developers
Classifier: Operating System :: OS Independent
Classifier: Programming Language :: Python :: 2.6
Classifier: Programming Language :: Python :: 2.7
Classifier: Programming Language :: Python :: 3.2
Classifier: Programming Language :: Python :: 3.3
Classifier: Programming Language :: Python :: 3.4
Classifier: Programming Language :: Python :: 3.5
Classifier: Programming Language :: Python :: 3.6
Classifier: Programming Language :: Python :: Implementation :: CPython
Classifier: Programming Language :: Python :: Implementation :: PyPy
Classifier: Topic :: Software Development :: Code Generators
Classifier: Topic :: Software Development :: Libraries :: Python Modules
Classifier: License :: OSI Approved :: BSD License
Requires-Dist: enum34
Requires-Dist: parse (>=1.6)
Requires-Dist: six
Requires-Dist: enum34; python_version=="2.6"
Requires-Dist: ordereddict; python_version=="2.6"
Requires-Dist: unittest2; python_version=="2.6"
Requires-Dist: enum34; python_version=="2.7"
Requires-Dist: enum34; python_version=="3.2"
Requires-Dist: enum34; python_version=="3.3"
Provides-Extra: develop
Requires-Dist: coverage; extra == 'develop'
Requires-Dist: pytest; extra == 'develop'
Requires-Dist: pytest-cov; extra == 'develop'
Requires-Dist: tox; extra == 'develop'
Provides-Extra: docs
Requires-Dist: sphinx (>=1.2); extra == 'docs'
